ShynaDatabase/MakeDatabase.py
ShynaDatabase/Shdatabase.py
ShynaDatabase/UpdateDistance.py
ShynaDatabase/__init__.py
ShynaDatabase-0.97.991.dist-info/LICENSE
ShynaDatabase-0.97.991.dist-info/METADATA
ShynaDatabase-0.97.991.dist-info/WHEEL
ShynaDatabase-0.97.991.dist-info/top_level.txt
ShynaDatabase-0.97.991.dist-info/RECORD
