Metadata-Version: 2.1
Name: ShynaDatabase
Version: 0.97.991
Summary: This package will take care of creating the database and querying the database.
Author: Shivam Sharma
Author-email: shivamsharma1913@gmail.com
License-File: LICENSE
Requires-Dist: mysql-connector-python
Requires-Dist: haversine
Requires-Dist: ShynaTime
Requires-Dist: setuptools
Requires-Dist: wheel
